bzfin/__init__.py
bzfin/forecaster.py
bzfin-0.0.7.dist-info/METADATA
bzfin-0.0.7.dist-info/WHEEL
bzfin-0.0.7.dist-info/top_level.txt
bzfin-0.0.7.dist-info/RECORD
