Metadata-Version: 2.1
Name: bzfin
Version: 0.0.7
Summary: Python package for forecasting baezeni data
Author: Marwan Musa
Author-email: marwanmusa@baezeni.com
Keywords: python,bz_forecast,bzfin,forecasting,time_series
Classifier: Development Status :: 3 - Alpha
Classifier: Intended Audience :: Education
Classifier: Programming Language :: Python :: 2
Classifier: Programming Language :: Python :: 3
Classifier: Operating System :: MacOS :: MacOS X
Classifier: Operating System :: Microsoft :: Windows
